{
  "type": "FeatureCollection",
  "features": [
    {
      "type": "Feature",
      "geometry": {
        "type": "Point",
        "coordinates": [70.23912, -97.25188]
      },
      "properties": {
        "iconurl": "icons/mini_map/icon_supply.png",
        "iconrotate": "20.983",
        "popupContent": "Amazing information about fixed_supply_crate will be found here!"
      },
      "bf2props": {
        "name": "cpname_khamisiyah_skirmish16_us_crate",
        "class": "ObjectPlacement",
        "name_object": "fixed_supply_crate",
        "team": "2",
        "obj1": "fixed_supply_crate",
        "obj2": "fixed_supply_crate",
        "maxspawn": "0.0",
        "minspawn": "0.0",
        "spawndelay": "false",
        "ttl": "99999.0"
      }
    },
    {
      "type": "Feature",
      "geometry": {
        "type": "Point",
        "coordinates": [65.18532, -67.075874]
      },
      "properties": {
        "iconurl": "icons/mini_map/icon_supply.png",
        "iconrotate": "1.019",
        "popupContent": "Amazing information about fixed_supply_crate will be found here!"
      },
      "bf2props": {
        "name": "cpname_khamisiyah_skirmish16_mec_crate",
        "class": "ObjectPlacement",
        "name_object": "fixed_supply_crate",
        "team": "1",
        "obj1": "fixed_supply_crate",
        "obj2": "fixed_supply_crate",
        "maxspawn": "0.0",
        "minspawn": "0.0",
        "spawndelay": "false",
        "ttl": "99999.0"
      }
    },
    {
      "type": "Feature",
      "geometry": {
        "type": "Point",
        "coordinates": [69.44481, -68.10919]
      },
      "properties": {
        "iconurl": "icons/mini_map/UAVtrailer.png",
        "iconrotate": "0",
        "popupContent": "Amazing information about mec_acv_btr60pu will be found here!"
      },
      "bf2props": {
        "name": "cpname_khamisiyah_skirmish16_mec_acv",
        "class": "ObjectPlacement",
        "name_object": "mec_acv_btr60pu",
        "team": "1",
        "obj1": "mec_acv_btr60pu",
        "obj2": "null",
        "maxspawn": "0.0",
        "minspawn": "0.0",
        "spawndelay": "false",
        "ttl": "99999.0"
      }
    },
    {
      "type": "Feature",
      "geometry": {
        "type": "Point",
        "coordinates": [74.876625, -97.71881]
      },
      "properties": {
        "iconurl": "icons/mini_map/UAVtrailer.png",
        "iconrotate": "0",
        "popupContent": "Amazing information about us_acv_stryker will be found here!"
      },
      "bf2props": {
        "name": "cpname_khamisiyah_skirmish16_us_acv",
        "class": "ObjectPlacement",
        "name_object": "us_acv_stryker",
        "team": "2",
        "obj1": "null",
        "obj2": "us_acv_stryker",
        "maxspawn": "0.0",
        "minspawn": "0.0",
        "spawndelay": "false",
        "ttl": "99999.0"
      }
    }
  ]
}